[
    {
        "algoritmo": "EQNAS",
        "bitstring": "010001011001011",
        "params": [
            48,
            0.005,
            96,
            1,
            3,
            4
        ],
        "real_mean": 80.53460365757564,
        "real_std": 0.0,
        "real_max": 80.53460365757564,
        "tiempo_medio": 27.790647109349568
    },
    {
        "algoritmo": "EQNAS",
        "bitstring": "111000100100010",
        "params": [
            256,
            0.01,
            128,
            4,
            1,
            3
        ],
        "real_mean": 80.21390689192805,
        "real_std": 0.0,
        "real_max": 80.21390689192805,
        "tiempo_medio": 29.55513342221578
    },
    {
        "algoritmo": "EQNAS",
        "bitstring": "111000100110010",
        "params": [
            256,
            0.01,
            128,
            8,
            1,
            3
        ],
        "real_mean": 79.8649403980221,
        "real_std": 0.0,
        "real_max": 79.8649403980221,
        "tiempo_medio": 3.963648955027262
    },
    {
        "algoritmo": "EQNAS",
        "bitstring": "101111011110010",
        "params": [
            128,
            5e-06,
            96,
            8,
            1,
            3
        ],
        "real_mean": 80.40638887787543,
        "real_std": 0.0,
        "real_max": 80.40638887787543,
        "tiempo_medio": 21.78317427635193
    },
    {
        "algoritmo": "EQNAS",
        "bitstring": "110001110010001",
        "params": [
            192,
            0.005,
            256,
            2,
            1,
            2
        ],
        "real_mean": 80.48791380059166,
        "real_std": 0.0,
        "real_max": 80.48791380059166,
        "tiempo_medio": 63.01239585876465
    }
]